README.rst
setup.py
django_restlayer.egg-info/PKG-INFO
django_restlayer.egg-info/SOURCES.txt
django_restlayer.egg-info/dependency_links.txt
django_restlayer.egg-info/requires.txt
django_restlayer.egg-info/top_level.txt
restlayer/__init__.py
restlayer/api.py
restlayer/models.py
restlayer/utils.py
restlayer/version.py