Metadata-Version: 1.0
Name: django-restlayer
Version: 0.8.5
Summary: HTTP REST toolkit for Django
Home-page: https://github.com/olivier-m/django-restlayer
Author: Olivier Meunier
Author-email: olivier@neokraft.net
License: MIT License
Platform: UNKNOWN
Classifier: Development Status :: 5 - Production/Stable
Classifier: Environment :: Web Environment
Classifier: Framework :: Django
Classifier: Intended Audience :: Developers
Classifier: License :: OSI Approved :: MIT License
Classifier: Operating System :: OS Independent
Classifier: Programming Language :: Python
Classifier: Topic :: Utilities
